{
  "FirstGreeting": {
    "phraseId": "FirstGreeting",
    "descriptor": {
      "idList": [
        "dialog1_1"
      ]
    },
    "tts": "    Привет,я Вокси! Как Вас зовут?"
  },
  "FirstGreetingKamenka": {
    "phraseId": "FirstGreetingKamenka",
    "descriptor": {
      "idList": [
        "dialog1_1"
      ]
    },
    "tts": "    Привет,я   ААллЁна! Как Вас зовут?"
  },
  "NameRepeatedQuery": {
    "phraseId": "NameRepeatedQuery",
    "descriptor": {
      "idList": [
        "rectification_1"
      ]
    },
    "tts": "Пожалуйста повторите ваше имя."
  },
  "FirstCallDescription": {
    "phraseId": "FirstCallDescription",
    "descriptor": {
      "idList": [
        "dialog1_2"
      ]
    },
    "tts": [ "Цена по городу 70 рублей.",
      "Цену за город, пожалуйста, уточните у водителя." ]
  },
  "LocationQuery": {
    "phraseId": "LocationQuery",
    "descriptor": {
      "idList": [
        "dialog1_2"
      ]
    },
    "tts": "Пожалуйста, скажите откуда и обязательно скажите куда вы поедете, или нажмите ноль если у вас есть другие вопросы."
  },
  "LocationRepeatedQuery": {
    "phraseId": "LocationRepeatedQuery",
    "descriptor": {
      "idList": [
        "rectification_2"
      ]
    },
    "tts": "Пожалуйста повторите где вы находитесь."
  },
  "DestinationQuery": {
    "phraseId": "DestinationQuery",
    "descriptor": {
      "idList": [
        "dialog1_3"
      ]
    },
    "tts": "Куда вы хотите добраться?"
  },
  "DestinationRepeatedQuery": {
    "phraseId": "DestinationRepeatedQuery",
    "descriptor": {
      "idList": [
        "rectification_3"
      ]
    },
    "tts": "Пожалуйста повторите куда хотите добраться."
  },
  "TripOnCarQuery": {
    "phraseId": "TripOnCarQuery",
    "descriptor": {
      "idList": [
        "dialog1_4_part1",
        {
          "data_category": "distance"
        },
        "preposition_for",
        {
          "data_category": "time"
        },
        "dialog1_7_part1",
        {
          "data_category": "price"
        },
        "dialog1_7_part2",
        "dialog1_7_part3"
      ]
    },
    "tts": "На машине вы преодолеете {distance} за {time}.  Стоимость поездки составит {price}. Вызвать вам машину?"
  },
  "DriverRecallPhrase": {
    "phraseId": "DriverRecallPhrase",
    "descriptor": {
      "idList": [
        "dialog1_5_part1",
        {
          "data_category": "time"
        }
      ]
    },
    "tts": " Я найду для вас машину и сразу перезвоню вам."
  },
  "DriverRecallKamenkaPhrase": {
    "phraseId": "DriverRecallKamenkaPhrase",
    "descriptor": {
      "idList": [
        "dialog1_5_part1",
        {
          "data_category": "time"
        }
      ]
    },
    "tts": " Я найду для вас машину и перезвоню вам через 5 минут."
  },
  "TalkEndFirstCallPhrase": {
    "phraseId": "TalkEndFirstCallPhrase",
    "descriptor": {
      "idList": [
        "dialog1_6"
      ]
    },
    "tts": "Я рада, что смогла вам помочь. Приятно было познакомится. Звоните в любое время."
  },
  "TalkEndPhrase": {
    "phraseId": "TalkEndPhrase",
    "descriptor": {
      "idList": [
        "dialog1_6"
      ]
    },
    "tts": "Я рада, что смогла вам помочь. Звоните в любое время."
  },
  "NoRoutePhrase": {
    "phraseId": "NoRoutePhrase",
    "descriptor": {
      "idList": [
        "rectification_4"
      ]
    },
    "tts": "Извините, к сожалению маршрут определить не могу."
  },
  "ImpossibleOrderPhrase": {
    "phraseId": "ImpossibleOrderPhrase",
    "descriptor": {
      "idList": [
        "rectification_5"
      ]
    },
    "tts": "Простите меня. Мои водители стараются отвезти каждого пассажира, но сейчас все они заняты. Я буду рада если вы позвоните чуть позже."
  },
  "PublicTransportQuery": {
    "phraseId": "PublicTransportQuery",
    "descriptor": {
      "idList": [
        "dialog1_8_part1",
        {
          "data_category": "stop"
        },
        "dialog1_8_part2",
        {
          "data_category": "number"
        },
        "dialog1_8_part3",
        {
          "data_category": "time"
        },
        "dialog1_8_part4",
        {
          "data_category": "stop"
        },
        "dialog1_8_part5"
      ]
    },
    "tts": ""
  },
  "CarTripRepeatedQuery": {
    "phraseId": "CarTripRepeatedQuery",
    "descriptor": {
      "idList": [
        "rectification_6"
      ]
    },
    "tts": " Пожалуйста, отвечайте  да или  нет: прислать за вами машину?"
  },
  "DriverWaitPhrase": {
    "phraseId": "DriverWaitPhrase",
    "descriptor": {
      "idList": [
        "notification_waiting"
      ]
    },
    "tts": "Машина подъехала. Номер {car_number}, цвет {car_color}. Цена поездки {price}. Счастливого пути!"
  },
  "DriverWaitAndDiscountPhrase": {
    "phraseId": "DriverWaitAndDiscountPhrase",
    "descriptor": {
      "idList": [
        "notification_waiting"
      ]
    },
    "tts": "Поздравляю! Я делаю вам скидку. {discount_names}. Цена поездки {price}. Машина уже подъехала. Приятного пути."
  },
  "NoDriverPhrase": {
    "phraseId": "NoDriverPhrase",
    "descriptor": {
      "idList": [
        "notification_no_driver"
      ]
    },
    "tts": "Простите. Мои водители стараются отвезти каждого пассажира, но сейчас все они заняты. Я буду рада если вы позвоните чуть позже."
  },
  "TalkErrorPhraseFileId": {
    "phraseId": "TalkErrorPhraseFileId",
    "descriptor": {
      "idList": [
        "notification_no_driver"
      ]
    },
    "tts": "Извините, вас плохо слышно, пожалуйста перезвоните."
  },
  "NameOnlyGreeting":{
    "phraseId": "NameOnlyGreeting",
    "descriptor": {
      "idList": []
    },
    "tts": "     {name}!"
  },
  "PersonalGreeting": {
    "phraseId": "PersonalGreeting",
    "descriptor": {
      "idList": [
        "dialog1_1"
      ]
    },
    "tts": "    Привет, {name}! Я рада вас  слышать!"
  },

  "PersonalMorningGreeting": {
    "phraseId": "PersonalMorningGreeting",
    "descriptor": {
      "idList": [
      ]
    },
    "tts": "    Доброе утро, {name}!"
  },
  "PersonalAfternoonGreeting": {
    "phraseId": "PersonalAfternoonGreeting",
    "descriptor": {
      "idList": [
      ]
    },
    "tts": "    Добрый день, {name}!"
  },
  "PersonalEveningGreeting": {
    "phraseId": "PersonalEveningGreeting",
    "descriptor": {
      "idList": [
      ]
    },
    "tts": "    Добрый вечер, {name}!"
  },
  "PersonalNightGreeting": {
    "phraseId": "PersonalNightGreeting",
    "descriptor": {
      "idList": [
      ]
    },
    "tts": "    Доброй ночи, {name}!"
  },
  "PersonalUNKDayPartGreeting": {
    "phraseId": "PersonalUNKDayPartGreeting",
    "descriptor": {
      "idList": [
      ]
    },
    "tts": "    Доброго времени суток, {name}!"
  },

  "MorningGreeting": {
    "phraseId": "MorningGreeting",
    "descriptor": {
      "idList": [
      ]
    },
    "tts": "    Доброе утро!"
  },
  "AfternoonGreeting": {
    "phraseId": "AfternoonGreeting",
    "descriptor": {
      "idList": [
      ]
    },
    "tts": "    Добрый день!"
  },
  "EveningGreeting": {
    "phraseId": "EveningGreeting",
    "descriptor": {
      "idList": [
      ]
    },
    "tts": "    Добрый вечер!"
  },
  "NightGreeting": {
    "phraseId": "NightGreeting",
    "descriptor": {
      "idList": [
      ]
    },
    "tts": "    Доброй ночи!"
  },
  "UNKDayPartGreeting": {
    "phraseId": "UNKDayPartGreeting",
    "descriptor": {
      "idList": [
      ]
    },
    "tts": "    Доброго времени суток!"
  },

  "OrderDetailsUnknown":{
    "phraseId": "OrderDetailsUnknown",
    "descriptor": {
      "idList": [
      ]
    },
    "tts": "    Цена Вашей поездки уточняется."
  },

  "OrderDetails": {
    "phraseId": "OrderDetails",
    "descriptor": {
      "idList": [
      ]
    },
    "tts": "    Ваша поездка будет стоить {price}, вы проедете {distance} за {time}."
  },
  "OrderDetailsOnlyPrice": {
    "phraseId": "OrderDetailsOnlyPrice",
    "descriptor": {
      "idList": [
      ]
    },
    "tts": "    Ваша поездка будет стоить {price}."
  },

  "OrderDetailsOnlyPriceKamenka": {
    "phraseId": "OrderDetailsOnlyPriceKamenka",
    "descriptor": {
      "idList": [
      ]
    },
    "tts": "    Цена вашей поездки {price}."
  },

  "OrderDetailsKamenka": {
    "phraseId": "OrderDetailsKamenka",
    "descriptor": {
      "idList": [
      ]
    },
    "tts": "    К Вам выехала машина с номером {car_number}. Цвет {car_color}. Цена вашей поездки {price}."
  },

 "CarWillArrivePhrase":{
   "phraseId": "CarWillArrivePhrase",
   "descriptor": {
      "idList": [
      ]
    },
    "tts": "     К Вам выехала машина с номером {car_number}. Цвет {car_color}. Цена поездки {price}. Я перезвоню вам, когда машина подъедет."
  },

 "OrderHasChangedPhrase":{
    "phraseId": "OrderHasChangedPhrase",
    "descriptor": {
      "idList": [
      ]
    },
    "tts": "     Извините. Я не правильно определила ваш адрес и допустила ошибку в расчетах. Правильная цена поездки {price}, вы проедете {distance} за {time}."
 },

  "Thanks_0":{
    "phraseId": "Thanks_0",
    "descriptor": {
      "idList": [
      ]
    },
    "tts": "Спасибо"
  },

  "Thanks_1":{
    "phraseId": "Thanks_1",
    "descriptor": {
      "idList": [
      ]
    },
    "tts": "Прекрасно"
  },

  "Thanks_2":{
    "phraseId": "Thanks_2",
    "descriptor": {
      "idList": [
      ]
    },
    "tts": "Отлично"
  },

  "Thanks_3":{
    "phraseId": "Thanks_3",
    "descriptor": {
      "idList": [
      ]
    },
    "tts": "Хорошо"
  },

  "Thanks_4":{
    "phraseId": "Thanks_4",
    "descriptor": {
      "idList": [
      ]
    },
    "tts": "Благодарю"
  },

  "OrderCreatedNotification":{
    "phraseId": "OrderCreatedNotification",
    "descriptor": {
      "idList": [
      ]
    },
    "tts": "Внимание! Создан новый заказ!"
  },

  "TripOnCarQueryWithDiscount": {
    "phraseId": "TripOnCarQueryWithDiscount",
    "descriptor": {
      "idList": [
      ]
    },
    "tts": "На машине вы преодолеете {distance} за {time}. Ваша поездка подпадает под действие акции {discount_names}. Итоговая стоимость поездки составит {price}. Вызвать вам машину?"
  },

   "TripOnCarQueryWithMultipleDiscounts": {
    "phraseId": "TripOnCarQueryWithMultipleDiscounts",
    "descriptor": {
      "idList": [
      ]
    },
    "tts": "На машине вы преодолеете {distance} за {time}. Ваша поездка подпадает под действие акций: {discount_names}. Итоговая стоимость поездки составит {price}. Вызвать вам машину?"
  },

  "ActiveOrderCancelQuery": {
    "phraseId": "ActiveOrderCancelQuery",
    "descriptor": {
      "idList": [
      ]
    },
    "tts": "Вы желаете отменить вашу текущую поездку?"
  },

  "ActiveOrderCancelRepeatQuery": {
    "phraseId": "ActiveOrderCancelRepeatQuery",
    "descriptor": {
      "idList": [
      ]
    },
    "tts": " Пожалуйста, отвечайте  да или  нет: отменить поездку?"
  },

  "ActiveOrderCanceledPhrase": {
    "phraseId": "ActiveOrderCanceledPhrase",
    "descriptor": {
      "idList": [
      ]
    },
    "tts": "Ваша поездка отменена."
  },

  "GoodSpeedPhrase":{
    "phraseId": "GoodSpeedPhrase",
    "descriptor": {
      "idList": [
      ]
    },
    "tts": "Счастливого пути."
  },

  "DoYouWantACarPhrase": {
    "phraseId": "DoYouWantACarPhrase",
    "descriptor": {
      "idList": [
      ]
    },
    "tts": " Вы хотите вызвать машину?"
  },

  "WeCallYouBackPhrase": {
    "phraseId": "WeCallYouBackPhrase",
    "descriptor": {
      "idList": [
      ]
    },
    "tts": " Спасибо. Мы рассмотрим ваше обращение и, свяжемся с вами"
  },

  "LeaveYourMessageQuery": {
    "phraseId": "LeaveYourMessageQuery",
    "descriptor": {
      "idList": [
      ]
    },
    "tts": " Мы принимаем ваши вопросы в автоматическом режиме. Оставьте голосовое сообщение, и служба поддержки свяжется с вами. Пожалуйста, говорите"
  },

  "RoomInShiftPhrase": {
    "phraseId": "RoomInShiftPhrase",
    "descriptor": {
      "idList": [
      ]
    },
    "tts": " Внимание! В сменах остались свободные места!"
  },

  "PriceInfohrase2": {
    "phraseId": "PriceInfohrase2",
    "descriptor": {
      "idList": [
      ]
    },
    "tts": " Цена поездки по городу до пяти километров 70 рублей до десяти километров 100 рублей. Цена поездки за город зависит от пункта назначения. Закажите машину. Водитель перезвонит вам. Уточните цену у водителя. Если цена вас не устроила, откажитесь от поездки."
  },

  "PriceInfohrase3": {
    "phraseId": "PriceInfohrase3",
    "descriptor": {
      "idList": [
      ]
    },
    "tts": " Цена поездки по городу 60 рублей. Заезд 30 рублей. Цена поездки за город уточняется у водителя. Для этого просто закажите машину. Водитель перезвонит вам. Уточните цену у водителя. Если цена вас не устроила, откажитесь от поездки."
  },
  
  "PriceInfohrase4": {
    "phraseId": "PriceInfohrase4",
    "descriptor": {
      "idList": [
      ]
    },
    "tts": " Цена поездки по городу 70 рублей. Цена поездки за город зависит от пункта назначения. Закажите машину. Водитель перезвонит вам. Уточните цену у водителя. Если цена вас не устроила, откажитесь от поездки."
  },

  "PreorderInfoPhrase": {
    "phraseId": "PreorderInfoPhrase",
    "descriptor": {
      "idList": [
      ]
    },
    "tts": " К сожалению, предварительные заказы автомобиля не принимаются."
  },

  "AskPassengerToRateDriverPhrase":{
    "phraseId": "AskPassengerToRateDriverPhrase",
    "descriptor": {
      "idList": [
      ]
    },
    "tts": "Пожалуйста, оцените работу водителя. Нажмите кнопку от 1 до 5 на вашем телефоне."
  },

  "ThanksForRatePhrase":{
    "phraseId": "ThanksForRatePhrase",
    "descriptor": {
      "idList": [
      ]
    },
    "tts": "Спасибо что вы помогаете Алене стать лучше. Досвидания"
  },

  "NewCityHelloPhrase":{
    "phraseId": "NewCityHelloPhrase",
    "descriptor": {
      "idList": [
      ]
    },
    "tts": "Привет, я ААллЁна! Индивидуальный помощник для совершения поездок по городу. Скоро я начну работу в вашем городе. А пока  я приглашаю на работу водителей с личным автомобилем."
  },

  "NewCityDoYouWantToWorkPhrase":{
    "phraseId": "NewCityDoYouWantToWorkPhrase",
    "descriptor": {
      "idList": [
      ]
    },
    "tts": "Если хотите стать водителем ААллЁны, нажмите цифру 1 на вашем телефоне."
  },

  "NewCityRecallAboutWorkPhrase":{
    "phraseId": "NewCityRecallAboutWorkPhrase",
    "descriptor": {
      "idList": [
      ]
    },
    "tts": "Спасибо, мы вам перезвоним."
  },

  "NewCityGoodbyePhrase":{
    "phraseId": "NewCityGoodbyePhrase",
    "descriptor": {
      "idList": [
      ]
    },
    "tts": "Досвидания."
  },

  "HelloPatient": {
    "phraseId": "HelloPatient",
    "descriptor": {
      "idList": [
      ]
    },
    "tts": "Здравствуйте! Вы позвонили в {name}!"
  },

  "OutCallHelloPatientPhrase": {
    "phraseId": "OutCallHelloPatientPhrase",
    "descriptor": {
      "idList": [
      ]
    },
    "tts": "Вас приветствует {name}!"
  },

  "IVRMenuPhrase": {
    "phraseId": "IVRMenuPhrase",
    "descriptor": {
      "idList": [
      ]
    },
    "tts": "Связаться с врачом, нажмите 1. Записаться в автоматическом режиме, нажмите 2"
  },

  "RecordQuery": {
    "phraseId": "RecordQuery",
    "descriptor": {
      "idList": [
      ]
    },
    "tts": "Назовите предпочтительную дату и время записи"
  },

  "GoogbyePhrase": {
    "phraseId": "GoogbyePhrase",
    "descriptor": {
      "idList": [
      ]
    },
    "tts": "Досвидания!"
  },

  "RecallPhrase": {
    "phraseId": "RecallPhrase",
    "descriptor": {
      "idList": [
      ]
    },
    "tts": "Мы перезвоним вам для подтверждения записи в течение часа."
  },

  "NotRealizedFeaturePhrase": {
    "phraseId": "NotRealizedFeaturePhrase",
    "descriptor": {
      "idList": [
      ]
    },
    "tts": "Эта возможность еще не реализована"
  },

  "DoctorInfoPhrase": {
    "phraseId": "DoctorInfoPhrase",
    "descriptor": {
      "idList": [
      ]
    },
    "tts": "Принимающий врач, {name}"
  },

  "DoctorAnsweredPhrase": {
    "phraseId": "DoctorAnsweredPhrase",
    "descriptor": {
      "idList": [
      ]
    },
    "tts": "Спасибо, что выбрали нас!"
  },

  "DoctorNotAnsweredPhrase": {
    "phraseId": "DoctorNotAnsweredPhrase",
    "descriptor": {
      "idList": [
      ]
    },
    "tts": "В данный момент врач не может ответить на ваш звонок."
  },

  "ConnectingPatientAndDoctorPhrase": {
    "phraseId": "ConnectingPatientAndDoctorPhrase",
    "descriptor": {
      "idList": [
      ]
    },
    "tts": "Подождите пока идет соединение с врачом."
  },

  "RecordInfoPhrase": {
    "phraseId": "RecordInfoPhrase",
    "descriptor": {
      "idList": [
      ]
    },
    "tts": "Вы записаны на {date}. Время записи {time}"
  },

  "RecordDatePhrase": {
    "phraseId": "RecordDatePhrase",
    "descriptor": {
      "idList": [
      ]
    },
    "tts": "Вы записаны на {date}"
  },

  "RecordTimePhrase": {
    "phraseId": "RecordTimePhrase",
    "descriptor": {
      "idList": [
      ]
    },
    "tts": "Время записи {time}"
  },

  "RecordCancelQuery": {
    "phraseId": "RecordCancelQuery",
    "descriptor": {
      "idList": [
      ]
    },
    "tts": "Хотите ли вы отменить запись?"
  },

  "RecordCancelRepeatQuery": {
    "phraseId": "RecordCancelRepeatQuery",
    "descriptor": {
      "idList": [
      ]
    },
    "tts": "Пожалуйста, отвечайте да или нет. Хотите ли вы отменить запись?"
  },

  "RecordCancelledPhrase": {
    "phraseId": "RecordCancelledPhrase",
    "descriptor": {
      "idList": [
      ]
    },
    "tts": "Запись отменена"
  },

  "HappyToHelpPhrase": {
    "phraseId": "HappyToHelpPhrase",
    "descriptor": {
      "idList": [
      ]
    },
    "tts": "Спасибо, что выбрали нас!"
  },

  "RecordDraftPhrase": {
    "phraseId": "RecordDraftPhrase",
    "descriptor": {
      "idList": [
      ]
    },
    "tts": "Ваша заявка на запись находится на стадии рассмотрения."
  },

  "RecordPrefixPhrase": {
    "phraseId": "RecordPrefixPhrase",
    "descriptor": {
      "idList": [
      ]
    },
    "tts": "Первая свободная запись на {date}"
  },

  "FreeRecordRelativeTimeFileId": {
    "phraseId": "FreeRecordRelativeTimeFileId",
    "descriptor": {
      "idList": [
      ]
    },
    "tts": "Ближайшая свободная запись {name}"
  },

  "FreeRecordDatePhrase": {
    "phraseId": "FreeRecordDatePhrase",
    "descriptor": {
      "idList": [
      ]
    },
    "tts": "На {date}"
  },

  "FreeRecordTimePhrase": {
    "phraseId": "FreeRecordTimePhrase",
    "descriptor": {
      "idList": [
      ]
    },
    "tts": "в {time}"
  },

  "WillYouComeFileId": {
    "phraseId": "WillYouComeFileId",
    "descriptor": {
      "idList": [
      ]
    },
    "tts": "Придете ли вы на прием?"
  },

  "RepeatWillYouComeFileId": {
    "phraseId": "RepeatWillYouComeFileId",
    "descriptor": {
      "idList": [
      ]
    },
    "tts": "Пожалуйста, отвечайте да или нет. Придете ли вы на прием?"
  },

  "NoFreeRecordFileId": {
    "phraseId": "NoFreeRecordFileId",
    "descriptor": {
      "idList": [
      ]
    },
    "tts": "К сожалению, свободных записей нет."
  }

}
